subtitle_alchemy/__init__.py
subtitle_alchemy/merge.py
subtitle_alchemy/align/__init__.py
subtitle_alchemy/align/_index.py
subtitle_alchemy/align/_tl.py
subtitle_alchemy/cli/__main__.py
subtitle_alchemy/cli/align.py
subtitle_alchemy/cli/generate.py
subtitle_alchemy/cli/squash.py
subtitle_alchemy/cli/transcribe.py
subtitle_alchemy/forger/__init__.py
subtitle_alchemy/forger/_srt.py
subtitle_alchemy/parser/__init__.py
subtitle_alchemy/parser/srt.py
subtitle_alchemy/parser/stt.py
subtitle_alchemy/utils/pinyin.py
subtitle_alchemy/utils/punc.py
subtitle_alchemy/utils/sl.py
subtitle_alchemy/utils/timeline.py
subtitle_alchemy-0.1.30.dist-info/entry_points.txt
subtitle_alchemy-0.1.30.dist-info/licenses/LICENSE
subtitle_alchemy-0.1.30.dist-info/WHEEL
subtitle_alchemy-0.1.30.dist-info/METADATA
subtitle_alchemy-0.1.30.dist-info/RECORD
