Metadata-Version: 2.4
Name: subtitle-alchemy
Version: 0.1.30
Summary: Process subtitle files with ease.
Author-email: Juan Cervantes <stall-breezes.0t@icloud.com>
Requires-Python: >=3.10,<3.14
Classifier: Development Status :: 3 - Alpha
Classifier: Intended Audience :: Developers
Classifier: Topic :: Software Development :: Build Tools
Classifier: License :: OSI Approved :: MIT License
Classifier: Programming Language :: Python :: 3
Classifier: Programming Language :: Python :: 3.11
License-File: LICENSE
Requires-Dist: click>=8.1.3
Requires-Dist: modelscope>=1.18.0
Requires-Dist: funasr>=1.1.6
Requires-Dist: pypinyin>=0.52.0
Requires-Dist: loguru>=0.7.2
Requires-Dist: torch>=2.7.1
Requires-Dist: torchvision>=0.22.1
Requires-Dist: torchaudio>=2.7.1
Project-URL: Homepage, https://github.com/ppmzhang2/subtitle-alchemy
Project-URL: Repository, https://github.com/ppmzhang2/subtitle-alchemy
